{"slug":"clay-guardian-a5e","name":"Clay Guardian","size":"Large","type":"Construct","subtype":"","group":null,"alignment":"","armor_class":14,"armor_desc":"","hit_points":133,"hit_dice":"14d10+56","speed":{"walk":25},"strength":20,"dexterity":10,"constitution":18,"intelligence":3,"wisdom":10,"charisma":1,"strength_save":null,"dexterity_save":null,"constitution_save":null,"intelligence_save":null,"wisdom_save":null,"charisma_save":null,"perception":null,"skills":{},"damage_vulnerabilities":"","damage_resistances":"","damage_immunities":"acid, poison, psychic; damage from nonmagical, non-adamantine weapons","condition_immunities":"charmed, fatigue, frightened, paralyzed, petrified, poisoned","senses":"darkvision 60 ft., passive Perception 10","languages":"understands the languages of its creator but can't speak","challenge_rating":"9","cr":9,"actions":[{"name":"Multiattack","desc":"The guardian attacks twice with its slam."},{"name":"Slam","desc":"Melee Weapon Attack: +9 to hit  reach 5 ft.  one target. Hit: 16 (2d10 + 5) bludgeoning damage. If the target is a creature  it makes a DC 15 Constitution saving throw. On a failure  its hit point maximum is reduced by an amount equal to the damage dealt. The target dies if its hit point maximum is reduced to 0. A greater restoration spell or similar magic removes the reduction."}],"reactions":"","legendary_desc":"","legendary_actions":"","special_abilities":[{"name":"Constructed Nature","desc":"Guardians dont require air, sustenance, or sleep."}],"spell_list":[],"page_no":261,"img_main":null,"document__slug":"menagerie","document__title":"Level Up Advanced 5e Monstrous Menagerie OGL","document__license_url":"http://open5e.com/legal"}