{"slug":"box-of-party-tricks-a5e","name":"Box of Party Tricks","type":"Wondrous Item","desc":"This small neat box contains 1d12 glowing vials. You can use an action to remove a vial and smash it to the ground, creating a randomly determined effect from the Box of Party Tricks table.\n\n## Table: Box of Party Tricks\n\n| **d8** | **Effect**                                                                                                                                                                                         |\n| ------ | -------------------------------------------------------------------------------------------------------------------------------------------------------------------------------------------------- |\n| 1      | A small bonfire appears in the nearest unoccupied 5-foot cube and remains for 1 minute. All other sources of flame within 50 feet double in brightness.                                            |\n| 2      | For the next minute you gain +1 bonus to ability checks, _attack rolls_ , damage rolls, and _saving throws_  using Strength.                                                                       |\n| 3      | You summon a small, fiercely loyal armored _weasel_  into your service (with 7 hit points and Armor Class 14 thanks to its miniature mithral outfit) that obeys only your commands.                |\n| 4      | A metal ball appears floating in your space and remains there until you say the command word, making it slam into the nearest hostile creature to deal 3d6 bludgeoning damage before disappearing. |\n| 5      | For the next 1d6 hours your voice becomes higher by an octave.                                                                                                                                     |\n| 6      | Until the next dawn you leave a trail of wildflowers wherever you walk.                                                                                                                            |\n| 7      | A pair of __boots of elvenkind_ appear in the nearest unoccupied square. After this effect has appeared once, any further results of 7 are rerolled.                                               |\n| 8      | All hostile creatures in a 30-foot radius are ensnared by ice. An ensnared creature is _grappled_  until it uses an action to make a DC 16 Strength check to break out.                            |","rarity":"Uncommon","requires_attunement":"","document__slug":"a5e","document__title":"Level Up Advanced 5e","document__url":"https://a5esrd.com/a5esrd"}