{"slug":"potion-of-animal-friendship","name":"Potion of Animal Friendship","type":"Potion","desc":"When you drink this potion, you can cast the _animal friendship_ spell (save DC 13) for 1 hour at will. Agitating this muddy liquid brings little bits into view: a fish scale, a hummingbird tongue, a cat claw, or a squirrel hair.","rarity":"uncommon","requires_attunement":"","document__slug":"wotc-srd","document__title":"5e Core Rules","document__url":"http://dnd.wizards.com/articles/features/systems-reference-document-srd"}